chromaspec.py
chromaspec-1.0.0.dist-info/licenses/LICENSE
chromaspec-1.0.0.dist-info/METADATA
chromaspec-1.0.0.dist-info/WHEEL
chromaspec-1.0.0.dist-info/entry_points.txt
chromaspec-1.0.0.dist-info/top_level.txt
chromaspec-1.0.0.dist-info/RECORD
