Metadata-Version: 2.4
Name: chromaspec
Version: 1.0.0
Summary: Python CLI tool for color palette analysis. Extract colors from images and SVG files, generate professional PDF swatches with HEX/RGB/CMYK values, frequency stats, pie charts, color harmonies, and WCAG accessibility ratings.
Author: Michail Semoglou
License: MIT
Project-URL: Homepage, https://github.com/MichailSemoglou/chromaspec
Project-URL: Repository, https://github.com/MichailSemoglou/chromaspec
Project-URL: Issues, https://github.com/MichailSemoglou/chromaspec/issues
Keywords: color,palette,color-extraction,image-analysis,svg,pdf,color-swatch,design,accessibility,wcag,cmyk,rgb,hex
Classifier: Development Status :: 5 - Production/Stable
Classifier: Environment :: Console
Classifier: Intended Audience :: Developers
Classifier: Intended Audience :: End Users/Desktop
Classifier: License :: OSI Approved :: MIT License
Classifier: Operating System :: OS Independent
Classifier: Programming Language :: Python :: 3
Classifier: Programming Language :: Python :: 3.8
Classifier: Programming Language :: Python :: 3.9
Classifier: Programming Language :: Python :: 3.10
Classifier: Programming Language :: Python :: 3.11
Classifier: Programming Language :: Python :: 3.12
Classifier: Topic :: Multimedia :: Graphics
Classifier: Topic :: Multimedia :: Graphics :: Graphics Conversion
Classifier: Topic :: Printing
Classifier: Topic :: Utilities
Requires-Python: >=3.8
License-File: LICENSE
Requires-Dist: reportlab>=4.0.0
Requires-Dist: Pillow>=10.0.0
Dynamic: license-file
